{
  "placeholderImages": [
    {
      "id": "hero-1",
      "description": "Stylish person looking out over a city",
      "imageUrl": "/images-product/hero-1.jpg",
      "imageHint": "fashion city"
    },
    {
      "id": "cat-mens",
      "description": "Man wearing a modern outfit",
      "imageUrl": "/images-product/cat-mens.jpg",
      "imageHint": "mens fashion"
    },
    {
      "id": "cat-womens",
      "description": "Woman in an elegant dress",
      "imageUrl": "/images-product/cat-womens.jpg",
      "imageHint": "womens fashion"
    },
    {
      "id": "cat-accessories",
      "description": "Close up of a watch and a bracelet",
      "imageUrl": "/images-product/cat-accessories.jpg",
      "imageHint": "fashion accessories"
    },
    {
      "id": "cat-winter",
      "description": "Person wearing a warm winter coat in a snowy environment",
      "imageUrl": "/images-product/cat-winter.jpg",
      "imageHint": "winter clothing"
    },
    {
      "id": "prod-1",
      "imageUrl": "/images-product/manteau-long-laine-hugo-boss.jpg",
      "imageHint": "men coat"
    },
    {
      "id": "prod-2",
      "imageUrl": "/images-product/doudoune-matelassee-moncler.jpg",
      "imageHint": "men jacket"
    },
    {
      "id": "prod-3",
      "imageUrl": "/images-product/parka-arctic-canada-goose.jpg",
      "imageHint": "men parka"
    },
    {
      "id": "prod-4",
      "imageUrl": "/images-product/manteau-cachemire-loro-piana-homme.jpg",
      "imageHint": "men coat"
    },
    {
      "id": "prod-5",
      "imageUrl": "/images-product/blouson-shearling-saint-laurent.jpg",
      "imageHint": "men jacket"
    },
    {
      "id": "prod-6",
      "imageUrl": "/images-product/pull-col-roule-laine-merinos-paul-smith.jpg",
      "imageHint": "men turtleneck"
    },
    {
      "id": "prod-7",
      "imageUrl": "/images-product/surchemise-doublee-acne-studios-homme.jpg",
      "imageHint": "men overshirt"
    },
    {
      "id": "prod-8",
      "imageUrl": "/images-product/doudoune-sans-manche-polo-ralph-lauren.jpg",
      "imageHint": "men vest"
    },
    {
      "id": "prod-9",
      "imageUrl": "/images-product/manteau-trench-double-burberry.jpg",
      "imageHint": "men trenchcoat"
    },
    {
      "id": "prod-10",
      "imageUrl": "/images-product/pull-torsade-epais-dior-homme.jpg",
      "imageHint": "men sweater"
    },
    {
      "id": "prod-11",
      "imageUrl": "/images-product/veste-technique-impermeable-tnf-black-series.jpg",
      "imageHint": "men jacket"
    },
    {
      "id": "prod-12",
      "imageUrl": "/images-product/robe-midi-en-soie-gucci.jpg",
      "imageHint": "women dress"
    },
    {
      "id": "prod-13",
      "imageUrl": "/images-product/blazer-croise-balmain.jpg",
      "imageHint": "women blazer"
    },
    {
      "id": "prod-14",
      "imageUrl": "/images-product/pull-col-roule-cachemire-loro-piana-femme.jpg",
      "imageHint": "women turtleneck"
    },
    {
      "id": "prod-15",
      "imageUrl": "/images-product/pantalon-large-en-laine-max-mara.jpg",
      "imageHint": "women trousers"
    },
    {
      "id": "prod-16",
      "imageUrl": "/images-product/jean-slim-premium-diesel.jpg",
      "imageHint": "women jeans"
    },
    {
      "id": "prod-17",
      "imageUrl": "/images-product/chemisier-en-soie-imprimee-saint-laurent.jpg",
      "imageHint": "women blouse"
    },
    {
      "id": "prod-18",
      "imageUrl": "/images-product/robe-courte-en-laine-prada.jpg",
      "imageHint": "women dress"
    },
    {
      "id": "prod-19",
      "imageUrl": "/images-product/manteau-long-en-cachemire-max-mara.jpg",
      "imageHint": "women coat"
    },
    {
      "id": "prod-20",
      "imageUrl": "/images-product/veste-courte-matelassee-moncler.jpg",
      "imageHint": "women jacket"
    },
    {
      "id": "prod-21",
      "imageUrl": "/images-product/pull-oversize-torsade-chloe.jpg",
      "imageHint": "women sweater"
    },
    {
      "id": "prod-22",
      "imageUrl": "/images-product/jupe-crayon-en-laine-hugo-boss.jpg",
      "imageHint": "women skirt"
    },
    {
      "id": "prod-23",
      "imageUrl": "/images-product/robe-longue-plissee-valentino.jpg",
      "imageHint": "women gown"
    },
    {
      "id": "prod-24",
      "imageUrl": "/images-product/chemise-en-coton-premium-burberry.jpg",
      "imageHint": "women shirt"
    },
    {
      "id": "prod-25",
      "imageUrl": "/images-product/robe-portefeuille-en-soie-diane-von-furstenberg.jpg",
      "imageHint": "women dress"
    },
    {
      "id": "prod-26",
      "imageUrl": "/images-product/pantalon-tailleur-dior-femme.jpg",
      "imageHint": "women trousers"
    },
    {
      "id": "prod-27",
      "imageUrl": "/images-product/manteau-long-laine-hugo-boss.jpg",
      "imageHint": "men coat"
    },
    {
      "id": "prod-28",
      "imageUrl": "/images-product/doudoune-matelassee-moncler.jpg",
      "imageHint": "men jacket"
    },
    {
      "id": "prod-29",
      "imageUrl": "/images-product/parka-arctic-canada-goose.jpg",
      "imageHint": "men parka"
    },
    {
      "id": "prod-30",
      "imageUrl": "/images-product/manteau-cachemire-loro-piana-homme.jpg",
      "imageHint": "men coat"
    },
    {
      "id": "prod-31",
      "imageUrl": "/images-product/blouson-shearling-saint-laurent.jpg",
      "imageHint": "men jacket"
    },
    {
      "id": "prod-32",
      "imageUrl": "/images-product/pull-col-roule-laine-merinos-paul-smith.jpg",
      "imageHint": "men turtleneck"
    },
    {
      "id": "prod-33",
      "imageUrl": "/images-product/surchemise-doublee-acne-studios-homme.jpg",
      "imageHint": "men overshirt"
    },
    {
      "id": "prod-34",
      "imageUrl": "/images-product/doudoune-sans-manche-polo-ralph-lauren.jpg",
      "imageHint": "men vest"
    },
    {
      "id": "prod-35",
      "imageUrl": "/images-product/manteau-trench-double-burberry.jpg",
      "imageHint": "men trenchcoat"
    },
    {
      "id": "prod-36",
      "imageUrl": "/images-product/pull-torsade-epais-dior-homme.jpg",
      "imageHint": "men sweater"
    },
    {
      "id": "prod-37",
      "imageUrl": "/images-product/veste-technique-impermeable-tnf-black-series.jpg",
      "imageHint": "men jacket"
    },
    {
      "id": "prod-38",
      "imageUrl": "/images-product/pantalon-thermique-nike-acg.jpg",
      "imageHint": "men pants"
    },
    {
      "id": "prod-39",
      "imageUrl": "/images-product/caban-laine-double-sandro.jpg",
      "imageHint": "men peacoat"
    },
    {
      "id": "prod-40",
      "imageUrl": "/images-product/doudoune-premium-armani-exchange.jpg",
      "imageHint": "men jacket"
    },
    {
      "id": "prod-41",
      "imageUrl": "/images-product/manteau-velours-zegna.jpg",
      "imageHint": "men coat"
    },
    {
      "id": "prod-42",
      "imageUrl": "/images-product/manteau-long-ceinture-laine-max-mara.jpg",
      "imageHint": "men coat"
    },
    {
      "id": "prod-43",
      "imageUrl": "/images-product/parka-fourrure-synthetique-canada-goose.jpg",
      "imageHint": "men parka"
    },
    {
      "id": "prod-44",
      "imageUrl": "/images-product/blouson-shearling-acne-studios-femme.jpg",
      "imageHint": "unisex jacket"
    },
    {
      "id": "prod-45",
      "imageUrl": "/images-product/pull-oversized-laine-jacquemus.jpg",
      "imageHint": "unisex sweater"
    },
    {
      "id": "prod-46",
      "imageUrl": "/images-product/manteau-puffer-xxl-zara-premium.jpg",
      "imageHint": "unisex coat"
    },
    {
      "id": "prod-gallery-1-1",
      "imageUrl": "/images-product/prod-gallery-1-1.jpg",
      "imageHint": "men shirt"
    },
    {
      "id": "prod-gallery-1-2",
      "imageUrl": "/images-product/prod-gallery-1-2.jpg",
      "imageHint": "shirt detail"
    },
    {
      "id": "prod-gallery-1-3",
      "imageUrl": "/images-product/prod-gallery-1-3.jpg",
      "imageHint": "fabric texture"
    },
    {
      "id": "avatar-1",
      "imageUrl": "/images-product/avatar-1.jpg",
      "imageHint": "person portrait"
    },
    {
      "id": "avatar-2",
      "imageUrl": "/images-product/avatar-2.jpg",
      "imageHint": "person portrait"
    },
    {
      "id": "avatar-3",
      "imageUrl": "/images-product/avatar-3.jpg",
      "imageHint": "person portrait"
    },
    {
      "id": "avatar-4",
      "imageUrl": "/images-product/avatar-4.jpg",
      "imageHint": "person portrait"
    },
    {
      "id": "avatar-5",
      "imageUrl": "/images-product/avatar-5.jpg",
      "imageHint": "person portrait"
    }
  ]
}